yaml2xbel/__init__.py
yaml2xbel/__main__.py
yaml2xbel-0.0.3.dist-info/LICENSE
yaml2xbel-0.0.3.dist-info/WHEEL
yaml2xbel-0.0.3.dist-info/METADATA
yaml2xbel-0.0.3.dist-info/RECORD
