Metadata-Version: 2.1
Name: yaml2xbel
Version: 0.0.3
Summary: XBEL generator from YAML
Author-email: Ngô Ngọc Đức Huy <huyngo@disroot.org>
Classifier: License :: OSI Approved :: Mozilla Public License 2.0 (MPL 2.0)
Classifier: Development Status :: 3 - Alpha
Classifier: Environment :: Console
Classifier: Intended Audience :: End Users/Desktop
Classifier: Operating System :: OS Independent
Classifier: Programming Language :: Python
Classifier: Programming Language :: Python :: 3
Requires-Dist: pyyaml
Project-URL: Home, https://sr.ht/~huyngo/yaml2xbel
